{
  "kind": "youtube#searchListResponse",
  "etag": "dxdo5IiaOFirMwylec-jcy1TGYQ",
  "nextPageToken": "CAEQAA",
  "regionCode": "US",
  "pageInfo": {
      "totalResults": 23,
      "resultsPerPage": 1
  },
  "items": [
      {
          "kind": "youtube#searchResult",
          "etag": "97dzRDn6uhDJVR3rhteMtoamCyg",
          "id": {
              "kind": "youtube#video",
              "videoId": "nJf62pMnjHA"
          },
          "snippet": {
              "publishedAt": "2022-11-19T23:23:54Z",
              "channelId": "UCluQ5yInbeAkkeCndNnUhpw",
              "title": "A Super Quick History of Peru",
              "description": "Pictures Requiring Attribution: Dtarazona: https://commons.wikimedia.org/wiki/File:Cabeza_clava_09_06122009.jpg Thayne ...",
              "thumbnails": {
                  "default": {
                      "url": "https://i.ytimg.com/vi/nJf62pMnjHA/default.jpg",
                      "width": 120,
                      "height": 90
                  },
                  "medium": {
                      "url": "https://i.ytimg.com/vi/nJf62pMnjHA/mqdefault.jpg",
                      "width": 320,
                      "height": 180
                  },
                  "high": {
                      "url": "https://i.ytimg.com/vi/nJf62pMnjHA/hqdefault.jpg",
                      "width": 480,
                      "height": 360
                  }
              },
              "channelTitle": "Mr History",
              "liveBroadcastContent": "none",
              "publishTime": "2022-11-19T23:23:54Z"
          }
      }
  ]
}